<?xml version='1.0' encoding='utf-8'?>
<!DOCTYPE hibernate-configuration PUBLIC
		"-//Hibernate/Hibernate Configuration DTD//EN"
		"http://www.hibernate.org/dtd/hibernate-configuration-3.0.dtd">
<hibernate-configuration>
	<session-factory>
		<property name="connection.url">jdbc:oracle:thin:@//10.30.242.238:1521/OSST2TST</property>
		<property name="connection.driver_class">oracle.jdbc.OracleDriver</property>
		<property name="dialect">org.hibernate.dialect.Oracle9iDialect</property>
		<property name="connection.username">TD_UDB_OWN</property>
		<property name="connection.password">TD_UDB_OWN</property>
		<property name="show_sql">true</property>
		<property name="connection.pool_size">40</property>
		<mapping class="com.hpe.dataload.generator.orm.model.TbsPatternSavedTEntity"/>
		<mapping resource="BlockDefTEntity.hbm.xml"/>
		<mapping resource="BlockDiagCodeMappingTEntity.hbm.xml"/>
	</session-factory>
</hibernate-configuration>